vmilabs/__init__.py
vmilabs/_logging.py
vmilabs/channel.py
vmilabs/device.py
vmilabs/wsChannel.py
vmilabs-0.2.0.dist-info/METADATA
vmilabs-0.2.0.dist-info/WHEEL
vmilabs-0.2.0.dist-info/top_level.txt
vmilabs-0.2.0.dist-info/RECORD
