Metadata-Version: 2.1
Name: vmilabs
Version: 0.2.0
Summary: official SDK for vmilabs product pillar
Home-page: https://github.com/openvmi/sdk.sandbox.python.git
Author: vmilabs
Author-email: kern_zhous@163.com
License: Apache-2.0
Keywords: vmilabs SDK
Platform: UNKNOWN
Requires-Python: >=3.6
Requires-Dist: websocket-client
Requires-Dist: netifaces
